literally/__init__.py
literally/base.py
literally/common.py
literally/errors.py
literally/utils.py
literally-0.1.2.dist-info/LICENSE
literally-0.1.2.dist-info/WHEEL
literally-0.1.2.dist-info/METADATA
literally-0.1.2.dist-info/RECORD
