Metadata-Version: 2.1
Name: literally
Version: 0.1.2
Summary: Pythonic implementation of the Sentinel Object Pattern
Author: Tom Bulled
Author-email: 26026015+tombulled@users.noreply.github.com
Requires-Python: >=3.8,<4.0
Classifier: Programming Language :: Python :: 3
Classifier: Programming Language :: Python :: 3.8
Classifier: Programming Language :: Python :: 3.9
